rtl/instruction_memory.sv
module instruction_memory(resetn, read_addr, instr_out);

    input resetn;
    input logic [31:0] read_addr;
    output reg [31:0] instr_out;

    // memory size
    parameter MEM_SIZE = 256;
    reg [31:0] mem[0:MEM_SIZE-1]; // 256 registers of 32 bits

    assign instr_out = mem[read_addr >> 2]; // assign instruction to what is at the memory in the read_addr
    integer k;
    
    always @ (negedge resetn)
    begin
        for (k = 0; k < MEM_SIZE; k = k + 1) begin
        mem[k] <= 32'h00000000;
        end
    end

endmodule

rtl/program_counter.sv
module program_counter(clk, resetn, pc_out);

    input clk;
    input resetn;

    output reg [31:0] pc_out;

    logic [31:0] next_pc;

    always @ (posedge clk)
    begin
        if(!resetn)
            pc_out <= 0;
        else
            pc_out <= next_pc;
    end
    assign next_pc = pc_out + 4;

endmodule

rtl/cpu_top.sv
module cpu_top(clk, resetn, pc_out, instr_out);

    input clk;
    input resetn;
    output reg [31:0] pc_out;
    output reg [31:0] instr_out;

    // PC
    program_counter pc_inst(.clk(clk),
    .resetn(resetn),
    .pc_out(pc_out));

    // IM
    instruction_memory im_inst(.resetn(resetn),
    .read_addr(pc_out),
    .instr_out(instr_out));

    // waveform directory
    initial begin
        $dumpfile("../waveforms/cpu_top.vcd");
        $dumpvars(0, cpu_top);
    end
endmodule

waveforms/cpu_top.vcd
$version Generated by VerilatedVcd $end
$timescale 1ps $end
 $scope module $rootio $end
  $var wire 1 # clk $end
  $var wire 1 $ resetn $end
  $var wire 32 % pc_out [31:0] $end
  $var wire 32 & instr_out [31:0] $end
 $upscope $end
 $scope module cpu_top $end
  $var wire 1 ' clk $end
  $var wire 1 ( resetn $end
  $var wire 32 ) pc_out [31:0] $end
  $var wire 32 * instr_out [31:0] $end
  $scope module im_inst $end
   $var wire 1 + resetn $end
   $var wire 32 , read_addr [31:0] $end
   $var wire 32 - instr_out [31:0] $end
   $var wire 32 3 MEM_SIZE [31:0] $end
   $var wire 32 . k [31:0] $end
  $upscope $end
  $scope module pc_inst $end
   $var wire 1 / clk $end
   $var wire 1 0 resetn $end
   $var wire 32 1 pc_out [31:0] $end
   $var wire 32 2 next_pc [31:0] $end
  $upscope $end
 $upscope $end
$enddefinitions $end


#0
1#
0$
b00000000000000000000000000000000 %
b00000000000000000000000000000000 &
1'
0(
b00000000000000000000000000000000 )
b00000000000000000000000000000000 *
0+
b00000000000000000000000000000000 ,
b00000000000000000000000000000000 -
b00000000000000000000000000000000 .
1/
00
b00000000000000000000000000000000 1
b00000000000000000000000000000100 2
b00000000000000000000000100000000 3
#5000
0#
0'
0/
#10000
1#
1$
b00000000010100000000000010010011 &
1'
1(
b00000000010100000000000010010011 *
1+
b00000000010100000000000010010011 -
1/
10
#15000
0#
0'
0/
#20000
1#
b00000000000000000000000000000100 %
b00000000101000000000000100010011 &
1'
b00000000000000000000000000000100 )
b00000000101000000000000100010011 *
b00000000000000000000000000000100 ,
b00000000101000000000000100010011 -
1/
b00000000000000000000000000000100 1
b00000000000000000000000000001000 2
#25000
0#
0'
0/
#30000
1#
b00000000000000000000000000001000 %
b00000000000000000000001100010011 &
1'
b00000000000000000000000000001000 )
b00000000000000000000001100010011 *
b00000000000000000000000000001000 ,
b00000000000000000000001100010011 -
1/
b00000000000000000000000000001000 1
b00000000000000000000000000001100 2
#35000
0#
0'
0/
#40000
1#
b00000000000000000000000000001100 %
b00000000001000001000000110110011 &
1'
b00000000000000000000000000001100 )
b00000000001000001000000110110011 *
b00000000000000000000000000001100 ,
b00000000001000001000000110110011 -
1/
b00000000000000000000000000001100 1
b00000000000000000000000000010000 2
#45000
0#
0'
0/
#50000
1#
b00000000000000000000000000010000 %
b00000010001000011000001000010011 &
1'
b00000000000000000000000000010000 )
b00000010001000011000001000010011 *
b00000000000000000000000000010000 ,
b00000010001000011000001000010011 -
1/
b00000000000000000000000000010000 1
b00000000000000000000000000010100 2
#55000
0#
0'
0/
#60000
1#
b00000000000000000000000000010100 %
b00000000100000100010001100000011 &
1'
b00000000000000000000000000010100 )
b00000000100000100010001100000011 *
b00000000000000000000000000010100 ,
b00000000100000100010001100000011 -
1/
b00000000000000000000000000010100 1
b00000000000000000000000000011000 2
#65000
0#
0'
0/
#70000
1#
b00000000000000000000000000011000 %
b01000000001000110000001010110011 &
1'
b00000000000000000000000000011000 )
b01000000001000110000001010110011 *
b00000000000000000000000000011000 ,
b01000000001000110000001010110011 -
1/
b00000000000000000000000000011000 1
b00000000000000000000000000011100 2
#75000
0#
0'
0/
#80000
1#
b00000000000000000000000000011100 %
b00000000011100010010001110110111 &
1'
b00000000000000000000000000011100 )
b00000000011100010010001110110111 *
b00000000000000000000000000011100 ,
b00000000011100010010001110110111 -
1/
b00000000000000000000000000011100 1
b00000000000000000000000000100000 2
#85000
0#
0'
0/
#90000
1#
b00000000000000000000000000100000 %
b01100111100000111000001110010011 &
1'
b00000000000000000000000000100000 )
b01100111100000111000001110010011 *
b00000000000000000000000000100000 ,
b01100111100000111000001110010011 -
1/
b00000000000000000000000000100000 1
b00000000000000000000000000100100 2
#95000
0#
0'
0/
#100000
1#
b00000000000000000000000000100100 %
b00000000001000001001010001100011 &
1'
b00000000000000000000000000100100 )
b00000000001000001001010001100011 *
b00000000000000000000000000100100 ,
b00000000001000001001010001100011 -
1/
b00000000000000000000000000100100 1
b00000000000000000000000000101000 2
#105000
0#
0'
0/
#110000
1#
b00000000000000000000000000101000 %
b11111110000111111111000001101111 &
1'
b00000000000000000000000000101000 )
b11111110000111111111000001101111 *
b00000000000000000000000000101000 ,
b11111110000111111111000001101111 -
1/
b00000000000000000000000000101000 1
b00000000000000000000000000101100 2
#115000
0#
0'
0/
#120000
1#
b00000000000000000000000000101100 %
b00000000000000000000000000010011 &
1'
b00000000000000000000000000101100 )
b00000000000000000000000000010011 *
b00000000000000000000000000101100 ,
b00000000000000000000000000010011 -
1/
b00000000000000000000000000101100 1
b00000000000000000000000000110000 2
#125000
0#
0'
0/
#130000
1#
b00000000000000000000000000110000 %
b00000000000000000000000000000000 &
1'
b00000000000000000000000000110000 )
b00000000000000000000000000000000 *
b00000000000000000000000000110000 ,
b00000000000000000000000000000000 -
1/
b00000000000000000000000000110000 1
b00000000000000000000000000110100 2
#135000
0#
0'
0/
#140000
1#
b00000000000000000000000000110100 %
1'
b00000000000000000000000000110100 )
b00000000000000000000000000110100 ,
1/
b00000000000000000000000000110100 1
b00000000000000000000000000111000 2
